mistercar_screenshooter/__init__.py
mistercar_screenshooter/capture.py
mistercar_screenshooter/constants.py
mistercar_screenshooter/exceptions.py
mistercar_screenshooter/platform/__init__.py
mistercar_screenshooter/platform/base.py
mistercar_screenshooter/platform/linux.py
mistercar_screenshooter/platform/macos.py
mistercar_screenshooter/platform/windows.py
mistercar_screenshooter/recording/__init__.py
mistercar_screenshooter/recording/bettercam_recorder.py
mistercar_screenshooter/recording/frame_buffer.py
mistercar_screenshooter/recording/video.py
mistercar_screenshooter/utils.py
mistercar_screenshooter-1.1.0.dist-info/LICENSE
mistercar_screenshooter-1.1.0.dist-info/METADATA
mistercar_screenshooter-1.1.0.dist-info/WHEEL
mistercar_screenshooter-1.1.0.dist-info/RECORD
