Metadata-Version: 2.3
Name: mistercar-screenshooter
Version: 1.1.0
Summary: A versatile, high-performance Python package for cross-platform screen capturing and recording
License: MIT
Keywords: screen capture,screenshot,video recording
Author: PypayaTech
Requires-Python: >=3.10,<4.0
Classifier: License :: OSI Approved :: MIT License
Classifier: Programming Language :: Python :: 3
Classifier: Programming Language :: Python :: 3.10
Classifier: Programming Language :: Python :: 3.11
Classifier: Programming Language :: Python :: 3.12
Classifier: Programming Language :: Python :: 3.13
Requires-Dist: bettercam (>=1.0.0,<2.0.0) ; sys_platform == "win32"
Requires-Dist: mss (>=9.0.2,<10.0.0)
Requires-Dist: numpy (>=2.0.1,<3.0.0)
Requires-Dist: opencv-python (>=4.10.0.84,<5.0.0.0)
Requires-Dist: pywin32 (>=306,<307) ; sys_platform == "win32"
Project-URL: Homepage, https://github.com/PypayaTech/mistercar-screenshooter
Project-URL: Repository, https://github.com/PypayaTech/mistercar-screenshooter
